Metadata-Version: 2.1
Name: minecraft-server-installer
Version: 1.5.4
Summary: minecraft server creator
Home-page: https://github.com/YaFlay/Minecraft_server_creating
Author: YaFlay
Author-email: yaflay@vk.com
License: UNKNOWN
Platform: UNKNOWN
Classifier: Programming Language :: Python :: 3
Classifier: License :: OSI Approved :: MIT License
Classifier: Operating System :: OS Independent
